{ "com_schedule" : [
    {
        "equipment": " ABB MV VFD(ID Fan)",
        "start_date" : "08.09.2025",
	"finished_date" : "16.09.2025",
        "engr_name":"Mr. Gu Jibing",
        "email" : "gujibing2000@163.com",
        "vendor" : "Mr.Xin",
        "status" : "Done"
     },
    {
        "equipment": " Schenck Process Engr",
        "start_date" : "25.09.2025",
	"finished_date" : "25.10.2025",
        "engr_name":"Mr. SONG ZHIFENG",
        "email" : "song.zhifeng@schenckprocess.com",
        "vendor" : "Schenck Process (China)",
        "status" : "Ongoing"
     },
    {
        "equipment": "Loesche Cold Comm",
        "start_date" : "29.09.2025",
	"finished_date" : "15.11.2025",
        "engr_name":"Mr. Alexander Stroettchen",
        "email" : "alexender@loesche.com",
        "vendor" : "LOESCHE",
        "status" : "Ongoing"
     }
  ]
}
  
